{
  "palavra": "lauto",
  "classe": "adjetivo",
  "silabacao": "l-u-o",
  "tonicidade": "paroxítona (sílaba tônica)",
  "significado": "Palavra erudita da língua portuguesa; termo de uso literário ou técnico.",
  "etimologia": "Do latim pungens.",
  "exemploCotidiano": "Hoje aprendi a palavra lauto e achei interessante.",
  "exemploLiterario": "A obra utilizava termos como lauto para criar atmosfera erudita.",
  "sinonimos": [
    "forte",
    "intenso"
  ],
  "dificuldade": 1,
  "curiosidade": "A palavra lauto tem origem clássica e uso literário."
}